README.rst
setup.py
cinit/__init__.py
cinit/templates.py
cinit.egg-info/PKG-INFO
cinit.egg-info/SOURCES.txt
cinit.egg-info/dependency_links.txt
cinit.egg-info/entry_points.txt
cinit.egg-info/top_level.txt
tests/__init__.py