Metadata-Version: 1.1
Name: cinit
Version: 0.1.0
Summary: Create a c/c++ directory structure
Home-page: https://github.com/juanpabloaj/cinit
Author: JuanPabloAJ
Author-email: jpabloaj@gmail.com
License: MIT
Platform: UNKNOWN
Classifier: Programming Language :: Python
Classifier: Programming Language :: Python :: 2.7
